{
 "date": "2026-07-20",
 "market": {
  "bull": true,
  "close": 7443.2798,
  "ma60": 7421.807195
 },
 "industries": [
  {
   "industry": "Financials",
   "ret20": 0.07804539798107091
  },
  {
   "industry": "Health Care",
   "ret20": 0.07292679538824842
  },
  {
   "industry": "Energy",
   "ret20": 0.06503280586646087
  },
  {
   "industry": "Real Estate",
   "ret20": 0.049380959157535154
  },
  {
   "industry": "Consumer Staples",
   "ret20": 0.033810000422336395
  }
 ],
 "leaders": [
  {
   "id": "PYPL",
   "name": "PayPal",
   "ret20": 0.3366266760762173
  },
  {
   "id": "VLO",
   "name": "Valero Energy",
   "ret20": 0.3258992805755394
  },
  {
   "id": "MPC",
   "name": "Marathon Petroleum",
   "ret20": 0.2980527767485901
  },
  {
   "id": "VEEV",
   "name": "Veeva Systems",
   "ret20": 0.2877364644487932
  },
  {
   "id": "PSX",
   "name": "Phillips 66",
   "ret20": 0.2567713976164683
  }
 ],
 "laggards": [
  {
   "id": "PYPL",
   "name": "PayPal",
   "score": 86,
   "close": 56.82,
   "industry": "Financials",
   "reasons": [
    "Outpacing sector over 5d",
    "+19.2% rebound in 5d",
    "-1% off 60-day high",
    "Volume 1.8× its 20d average"
   ]
  },
  {
   "id": "BNY",
   "name": "BNY Mellon",
   "score": 79,
   "close": 156.93,
   "industry": "Financials",
   "reasons": [
    "⚠️ Unfilled gap overhead",
    "⚠️ False breakout (lost 5MA & neckline)",
    "Outpacing sector over 5d",
    "+3.7% rebound in 5d",
    "-4% off 60-day high",
    "Volume 1.2× its 20d average"
   ]
  },
  {
   "id": "MTB",
   "name": "M&T Bank",
   "score": 79,
   "close": 249.44,
   "industry": "Financials",
   "reasons": [
    "Outpacing sector over 5d",
    "+2.8% rebound in 5d",
    "-2% off 60-day high",
    "Volume 1.2× its 20d average"
   ]
  },
  {
   "id": "STT",
   "name": "State Street Corporation",
   "score": 79,
   "close": 182.58,
   "industry": "Financials",
   "reasons": [
    "Outpacing sector over 5d",
    "+2.5% rebound in 5d",
    "-5% off 60-day high",
    "Volume 1.3× its 20d average"
   ]
  },
  {
   "id": "ABT",
   "name": "Abbott Laboratories",
   "score": 76,
   "close": 101.66,
   "industry": "Health Care",
   "reasons": [
    "Outpacing sector over 5d",
    "+11.2% rebound in 5d",
    "-1% off 60-day high",
    "Volume 1.4× its 20d average"
   ]
  }
 ],
 "action": {
  "state": "bull",
  "engine": "current",
  "hold_days": 20,
  "test_range": "2025-08-28 ~ 2026-05-22",
  "strong": [
   {
    "id": "PYPL",
    "name": "PayPal",
    "score": 86,
    "close": 56.82,
    "trust_net5": 0,
    "trust_streak": 0,
    "radar": null
   },
   {
    "id": "BNY",
    "name": "BNY Mellon",
    "score": 79,
    "close": 156.93,
    "trust_net5": 0,
    "trust_streak": 0,
    "radar": null
   },
   {
    "id": "MTB",
    "name": "M&T Bank",
    "score": 79,
    "close": 249.44,
    "trust_net5": 0,
    "trust_streak": 0,
    "radar": null
   },
   {
    "id": "STT",
    "name": "State Street Corporation",
    "score": 79,
    "close": 182.58,
    "trust_net5": 0,
    "trust_streak": 0,
    "radar": null
   },
   {
    "id": "ABT",
    "name": "Abbott Laboratories",
    "score": 76,
    "close": 101.66,
    "trust_net5": 0,
    "trust_streak": 0,
    "radar": null
   }
  ],
  "balanced": [],
  "stats": {
   "strong": {
    "win_abs": 53.1,
    "ret_net": 6.72,
    "excess": 0.69,
    "p10": -15.9,
    "n": 885
   },
   "strong_planB": {
    "win_abs": 59.7,
    "ret_net": 0.82,
    "excess": -1.07
   },
   "floor": {
    "win": 51.2,
    "excess": 4.82,
    "p10": -17.54,
    "n": 404
   },
   "exit_ma_stop": {
    "win": 11.8,
    "excess": -9.03
   },
   "exit_hold_full": {
    "win": 56.9,
    "excess": 9.21
   },
   "us_current": {
    "win": 33.8,
    "excess": -2.76,
    "p10": -24.15,
    "n": 2796
   }
  },
  "radar": null,
  "plans": {
   "A": {
    "win_abs": 53.1,
    "ret_net": 6.72,
    "excess": 0.69,
    "p10": -15.9,
    "n": 885
   },
   "B": {
    "win_abs": 59.7,
    "ret_net": 0.82,
    "excess": -1.07
   }
  }
 }
}