{"date": "2026-05-18", "industries": ["Energy", "Information Technology", "Consumer Staples", "Real Estate", "Communication Services", "Financials", "Industrials", "Utilities", "Health Care", "Materials"], "leaders": ["DDOG", "FTNT", "PANW", "CRWD", "CSCO", "PM", "MPC", "FFIV", "CBOE", "GEN", "TRGP", "HAL", "BEN", "MNST", "DOC"], "laggards": [{"id": "TYL", "name": "Tyler Technologies", "score": 97, "close": 320.79}, {"id": "CSGP", "name": "CoStar Group", "score": 92, "close": 33.2}, {"id": "ACN", "name": "Accenture", "score": 90, "close": 177.55}, {"id": "CTSH", "name": "Cognizant", "score": 90, "close": 51.4}, {"id": "MSI", "name": "Motorola Solutions", "score": 90, "close": 410.27}, {"id": "DG", "name": "Dollar General", "score": 88, "close": 106.23}, {"id": "STZ", "name": "Constellation Brands", "score": 88, "close": 147.58}, {"id": "XOM", "name": "ExxonMobil", "score": 85, "close": 160.49}, {"id": "ANET", "name": "Arista Networks", "score": 82, "close": 141.71}, {"id": "CDW", "name": "CDW Corporation", "score": 82, "close": 103.4267}, {"id": "INTU", "name": "Intuit", "score": 82, "close": 403.16}, {"id": "NOW", "name": "ServiceNow", "score": 82, "close": 103.42}, {"id": "ROP", "name": "Roper Technologies", "score": 82, "close": 331.01}, {"id": "AJG", "name": "Arthur J. Gallagher & Co.", "score": 79, "close": 206.4628}, {"id": "FDS", "name": "FactSet", "score": 79, "close": 223.2607}, {"id": "FIS", "name": "Fidelity National Information Services", "score": 79, "close": 42.8803}, {"id": "BR", "name": "Broadridge Financial Solutions", "score": 77, "close": 150.62}, {"id": "CVX", "name": "Chevron Corporation", "score": 75, "close": 194.34}, {"id": "OXY", "name": "Occidental Petroleum", "score": 75, "close": 59.4255}, {"id": "CRM", "name": "Salesforce", "score": 72, "close": 179.018}]}