{"date": "2026-07-17", "industries": ["Health Care", "Financials", "Real Estate", "Energy", "Consumer Staples", "Utilities", "Communication Services", "Industrials", "Materials", "Consumer Discretionary"], "leaders": ["PYPL", "TECH", "VLO", "MPC", "PSX", "TRV", "INCY", "WELL", "VTR", "UNP", "DOC", "DHR", "ABT", "EXPD", "EG"], "laggards": [{"id": "PYPL", "name": "PayPal", "score": 83, "close": 56.56}, {"id": "ABT", "name": "Abbott Laboratories", "score": 79, "close": 100.68}, {"id": "CVS", "name": "CVS Health", "score": 71, "close": 107.47}, {"id": "HUM", "name": "Humana", "score": 71, "close": 400.0}, {"id": "BAC", "name": "Bank of America", "score": 68, "close": 61.27}, {"id": "BNY", "name": "BNY Mellon", "score": 68, "close": 157.13}, {"id": "CFG", "name": "Citizens Financial Group", "score": 68, "close": 72.39}, {"id": "FANG", "name": "Diamondback Energy", "score": 67, "close": 195.54}, {"id": "TPL", "name": "Texas Pacific Land Corporation", "score": 67, "close": 415.7}, {"id": "XOM", "name": "ExxonMobil", "score": 67, "close": 147.36}, {"id": "PLD", "name": "Prologis", "score": 66, "close": 149.79}, {"id": "OTIS", "name": "Otis Worldwide", "score": 66, "close": 73.45}, {"id": "WBD", "name": "Warner Bros. Discovery", "score": 63, "close": 26.87}, {"id": "ABBV", "name": "AbbVie", "score": 61, "close": 254.49}, {"id": "NEE", "name": "NextEra Energy", "score": 61, "close": 88.8}, {"id": "DG", "name": "Dollar General", "score": 60, "close": 125.75}, {"id": "CHRW", "name": "C.H. Robinson", "score": 60, "close": 208.5}, {"id": "CTAS", "name": "Cintas", "score": 60, "close": 204.45}, {"id": "JBHT", "name": "J.B. Hunt", "score": 60, "close": 291.41}, {"id": "FE", "name": "FirstEnergy", "score": 57, "close": 48.53}]}