{
 "date": "2026-06-22",
 "market": {
  "bull": true,
  "close": 47741.51,
  "ma60": 40244.848
 },
 "industries": [
  {
   "industry": "金融業",
   "ret20": 0.2565920727709028
  },
  {
   "industry": "造紙工業",
   "ret20": 0.20408505317215542
  },
  {
   "industry": "塑膠工業",
   "ret20": 0.1580110497237568
  },
  {
   "industry": "金融保險業",
   "ret20": 0.13654015643935224
  },
  {
   "industry": "玻璃陶瓷",
   "ret20": 0.13166909493171297
  }
 ],
 "leaders": [
  {
   "id": "2892",
   "name": "第一金",
   "ret20": 0.17241379310344818
  },
  {
   "id": "2408",
   "name": "南亞科",
   "ret20": 0.6264090177133654
  },
  {
   "id": "2492",
   "name": "華新科",
   "ret20": 1.1094017094017095
  },
  {
   "id": "1303",
   "name": "南亞",
   "ret20": 0.7589388696655133
  },
  {
   "id": "6271",
   "name": "同欣電",
   "ret20": 0.19149411797580118
  }
 ],
 "laggards": [
  {
   "id": "7734",
   "name": "印能科技",
   "score": 70,
   "close": 3560.0,
   "industry": "半導體業",
   "reasons": [
    "⚠️ 注意股",
    "投信連買 5 天",
    "外資 5 日買超 54 張",
    "營收年增 137%",
    "站上 5/10/20 日均線",
    "距 60 日高點 -23%"
   ]
  },
  {
   "id": "3037",
   "name": "欣興",
   "score": 60,
   "close": 1005.0,
   "industry": "電子零組件業",
   "reasons": [
    "投信 5 日買超 2,242 張",
    "外資 5 日買超 4,704 張",
    "營收年增 32%",
    "站上 5/10/20 日均線",
    "距 60 日高點 -11%"
   ]
  },
  {
   "id": "6462",
   "name": "神盾",
   "score": 60,
   "close": 122.0,
   "industry": "半導體業",
   "reasons": [
    "投信 5 日買超 5 張",
    "外資 5 日買超 113 張",
    "營收年增 136%",
    "站上 5/10/20 日均線",
    "距 60 日高點 -24%"
   ]
  },
  {
   "id": "8054",
   "name": "安國",
   "score": 60,
   "close": 113.5,
   "industry": "半導體業",
   "reasons": [
    "外資 5 日買超 2,968 張",
    "營收年增 383%",
    "站上 5/10/20 日均線",
    "距 60 日高點 -13%",
    "🔥 爆大量:今日量達均量 2.4 倍"
   ]
  }
 ]
}