{"date": "2026-03-27", "industries": ["文化創意業", "塑膠工業", "電子通路業", "油電燃氣業", "建材營造", "其他", "通信網路業", "其他電子業", "貿易百貨", "光電業"], "leaders": ["1309", "4577", "2419", "3062", "4760"], "laggards": [{"id": "6442", "name": "光聖", "score": 79, "close": 2115.0}, {"id": "4979", "name": "華星光", "score": 72, "close": 396.5}, {"id": "7728", "name": "光焱科技", "score": 70, "close": 756.0}, {"id": "4585", "name": "達明", "score": 69, "close": 301.5}, {"id": "6139", "name": "亞翔", "score": 66, "close": 574.0}, {"id": "6196", "name": "帆宣", "score": 64, "close": 293.0}, {"id": "2317", "name": "鴻海", "score": 57, "close": 199.5}, {"id": "6691", "name": "洋基工程", "score": 56, "close": 592.0}, {"id": "7717", "name": "萊德光電-KY", "score": 55, "close": 771.0}, {"id": "2354", "name": "鴻準", "score": 53, "close": 52.2}, {"id": "3234", "name": "光環", "score": 52, "close": 94.1}, {"id": "1301", "name": "台塑", "score": 51, "close": 46.9}]}